{
  "video_id": "-pXsceBZ-uI",
  "title": "ZomBN1 - A Game all About Brighton, With Zombies!",
  "discourse_topic_id": 606,
  "body": "<div class=\"youtube-onebox lazy-video-container\" data-video-id=\"-pXsceBZ-uI\" data-video-title=\"ZomBN1 - A Game all About Brighton, With Zombies!\" data-video-start-time=\"\" data-provider-name=\"youtube\">\n  <a href=\"https://www.youtube.com/watch?v=-pXsceBZ-uI\" target=\"_blank\" class=\"video-thumbnail\" rel=\"noopener nofollow ugc\">\n    <img class=\"youtube-thumbnail\" src=\"https://dungeondive.quest/uploads/default/original/2X/1/1db36cf39a4222569f9f77425b14834fd03fa209.jpeg\" title=\"ZomBN1 - A Game all About Brighton, With Zombies!\" data-dominant-color=\"706341\" width=\"690\" height=\"388\">\n  </a>\n</div>\n\n<p>Daniel (<a class=\"mention\" href=\"/u/dungeondive\">@Dungeondive</a>) takes a look at <strong>Zombie In One</strong>, the second edition of Paul Stapleton’s quirky zombie survival game set in Brighton. Building on the charm of his earlier title <em>B In One</em>, this version asks what happens when the bustling, artsy seaside town is overrun by zombies.</p>\n<p>Players take on the roles of local residents trying to escape while competing for points by completing objectives, surviving encounters, and fighting off zombies. One player controls the zombies in an asymmetrical game of survival and sabotage. The game features beautifully illustrated standees, whimsical item and encounter cards, and a board filled with delightful details that give it a <em>Where’s Waldo</em> or <em>Mad Magazine</em> vibe.</p>\n<p>Daniel explores both the standard competitive mode and his own custom solo/co-op rules, which strip out the “take that” elements to focus on the narrative fun. He shares house rules, tweaks to AI behavior, and even adds new systems like zombie escalation and alternate victory conditions. The game’s light mechanics, narrative flavor, and artistic charm make it a standout in the crowded zombie genre—especially for those seeking a more humorous take.</p>\n<p>If you love imaginative, character-driven board games with a strong sense of place and don’t mind rolling with a few house rules, Zombie In One might just infect your heart.</p>",
  "recovered_at": "2026-04-09T03:54:46+00:00"
}