{
  "video_id": "0A3d0lovA9c",
  "title": "Sol Cesto - Press Your Luck - The Game (Digital Dive)",
  "discourse_topic_id": 1164,
  "body": "<div class=\"youtube-onebox lazy-video-container\" data-video-id=\"0A3d0lovA9c\" data-video-title=\"Sol Cesto - Press Your Luck - The Game (Digital Dive)\" data-video-start-time=\"\" data-provider-name=\"youtube\">\n  <a href=\"https://www.youtube.com/watch?v=0A3d0lovA9c\" target=\"_blank\" class=\"video-thumbnail\" rel=\"noopener\">\n    <img class=\"youtube-thumbnail\" src=\"https://dungeondive.quest/uploads/default/original/2X/b/b1ba74656719da02ebc807ca658879ffa990b3fd.jpeg\" title=\"Sol Cesto - Press Your Luck - The Game (Digital Dive)\" data-dominant-color=\"64564D\" width=\"690\" height=\"388\">\n  </a>\n</div>\n\n<hr>\n<p><strong>Digital Dive</strong> — Daniel (<a class=\"mention\" href=\"/u/dungeondive\">@dungeondive</a>) checks out <em>Sol Cesto</em>, a roguelike dungeon crawler on Steam (~$12, early access).</p>\n<p>The game is pure press-your-luck. You click a row and have percentage chances to interact with each tile — monsters, treasure, traps, or healing. Combat alternates between physical and magical, and progression means unlocking attractions (biases toward certain tile types) and permanent upgrades between runs.</p>\n<p><strong>What stands out:</strong></p>\n<ul>\n<li>Gorgeous whimsical art style reminiscent of <em>Paupers’ Ladder</em></li>\n<li>Dead simple mechanics, but genuinely tense decisions</li>\n<li>Unlockable heroes, stone/metal statue boons, and a meta-progression loop</li>\n<li>Gold only banks if you find a bucket and pull it up — die without banking and you lose it all</li>\n<li>Would make a perfect mobile game (meant as a compliment)</li>\n</ul>\n<p>Daniel didn’t reach the boss on his demo run, but had a great time with the charm, humour, and tension. Press-your-luck is one of his favourite mechanisms, and Sol Cesto nails it.</p>\n<p><em>Have you tried Sol Cesto or similar press-your-luck roguelikes? Does the art style appeal to you?</em></p>",
  "recovered_at": "2026-04-09T03:54:23+00:00"
}