{
  "video_id": "IJdPXXMpYPk",
  "title": "Hobbycast Episode 16: A Casual Conversation with Dustin Freund, Designer of The Ghosts Betwixt",
  "discourse_topic_id": 275,
  "body": "<div class=\"youtube-onebox lazy-video-container\" data-video-id=\"IJdPXXMpYPk\" data-video-title=\"Hobbycast Episode 16: A Casual Conversation with Dustin Freund, Designer of The Ghosts Betwixt\" data-video-start-time=\"\" data-provider-name=\"youtube\">\n  <a href=\"https://www.youtube.com/watch?v=IJdPXXMpYPk\" target=\"_blank\" class=\"video-thumbnail\" rel=\"noopener nofollow ugc\">\n    <img class=\"youtube-thumbnail\" src=\"https://dungeondive.quest/uploads/default/original/1X/2e57472c94df08826b8436c83443803e2bbc142b.jpeg\" title=\"Hobbycast Episode 16: A Casual Conversation with Dustin Freund, Designer of The Ghosts Betwixt\" data-dominant-color=\"646C4C\" width=\"480\" height=\"360\">\n  </a>\n</div>\n\n<p>Daniel (<a class=\"mention\" href=\"/u/dungeondive\">@Dungeondive</a>) interviews Dustin Freund, the designer of <em>The Ghosts Betwixt</em>, to discuss the development of the game and the challenges of crowdfunding on Kickstarter. They dive into topics such as early inspirations for <em>The Ghosts Betwixt</em>, including <em>HeroQuest</em>, <em>Imperial Assault</em>, and <em>Shadows of Brimstone</em>, which shaped the game’s strategic mechanics, particularly its initiative system. Dustin explains how the game’s family of protagonists—Bill, Joan, Maddox, and Evelyn—bring an emotional core to the dungeon-crawling experience, making the game unique in a genre often dominated by more typical adventurer archetypes.</p>\n<p>They also explore the impact of components, such as standees versus miniatures, and the decision to incorporate everyday objects as loot in the game to enhance immersion. Dustin shares his thoughts on the importance of accessibility and engagement in both the gameplay and the rulebook, citing how <em>The Ghosts Betwixt</em> uses time as a currency during setup, allowing players to customize their party and gear in an intuitive way.</p>\n<p>The conversation wraps up with insights into Dustin’s plans for <em>The Ghosts Betwixt: Chapter Two</em>, which will expand the original game’s world without the need for a massive new box. Players can expect new storylines, an overworld map, and more flexibility in mission lengths. He emphasizes keeping the game accessible for both veteran players and newcomers, ensuring that Chapter Two can be enjoyed even if you haven’t played the first chapter.</p>\n<p><a href=\"https://theghostsbetwixt.com\" class=\"onebox\" target=\"_blank\" rel=\"noopener nofollow ugc\">https://theghostsbetwixt.com</a></p>\n<p><a href=\"https://theghostsbetwixt.com\" rel=\"noopener nofollow ugc\"><img src=\"https://dungeondive.quest/uploads/default/original/1X/e44d91e8a6f464d465cb0324ffdbd99555f317bc.jpeg\" alt=\"image\" data-base62-sha1=\"wzF3tKFI6HVLsP8KEA5GQlTtz9q\" width=\"690\" height=\"229\"></a></p>",
  "recovered_at": "2026-04-09T03:56:18+00:00"
}